abu_quant-0.0.1.dist-info/DESCRIPTION.rst
abu_quant-0.0.1.dist-info/METADATA
abu_quant-0.0.1.dist-info/metadata.json
abu_quant-0.0.1.dist-info/RECORD
abu_quant-0.0.1.dist-info/top_level.txt
abu_quant-0.0.1.dist-info/WHEEL
abupy/__init__.py
