Metadata-Version: 2.0
Name: abu-quant
Version: 0.0.1
Summary: 股票量化
Home-page: UNKNOWN
Author: 阿布
Author-email: steven.wu.ven@gmail.com
License: UNKNOWN
Keywords: 阿布,abu,quant,quantization,量化,爬虫,crawler,spider,scrapy,stock,股票,ML,机器学习,深度学习,machine learning,deep learning
Platform: any
